[
  {
    "id": 31999,
    "namespaceId": 0,
    "itemPublicationId": 1611362,
    "itemId": 368717,
    "itemType": 64,
    "score": 0,
    "status": 0,
    "creationDate": {
      "dayOfMonth": 26,
      "hour": 21,
      "minute": 49,
      "month": "",
      "monthValue": 7,
      "nano": 0,
      "second": 52,
      "year": 2006,
      "dayOfWeek": "",
      "dayOfYear": 8
    },
    "lastModifiedDate": {
      "dayOfMonth": 26,
      "hour": 21,
      "minute": 49,
      "month": "",
      "monthValue": 7,
      "nano": 0,
      "second": 52,
      "year": 2006,
      "dayOfWeek": "",
      "dayOfYear": 8
    },
    "content": "Test comment with some content. Id of this comment is 31999.",
    "moderator": null,
    "moderatedDate": {
      "dayOfMonth": 26,
      "hour": 21,
      "minute": 49,
      "month": "",
      "monthValue": 7,
      "nano": 0,
      "second": 52,
      "year": 2006,
      "dayOfWeek": "",
      "dayOfYear": 8
    },
    "parentId": 0,
    "parent": null,
    "children": null,
    "user": {
      "id": 1,
      "name": "user 1",
      "emailAddress": "user1@sdl.com",
      "externalId": null
    },
    "idLong": 31999
  },
  {
    "id": 99393,
    "namespaceId": 0,
    "itemPublicationId": 1611362,
    "itemId": 368717,
    "itemType": 64,
    "score": 0,
    "status": 0,
    "creationDate": {
      "dayOfMonth": 9,
      "hour": 5,
      "minute": 27,
      "month": "",
      "monthValue": 2,
      "nano": 0,
      "second": 1,
      "year": 2000,
      "dayOfWeek": "",
      "dayOfYear": 212
    },
    "lastModifiedDate": {
      "dayOfMonth": 9,
      "hour": 5,
      "minute": 27,
      "month": "",
      "monthValue": 2,
      "nano": 0,
      "second": 1,
      "year": 2000,
      "dayOfWeek": "",
      "dayOfYear": 212
    },
    "content": "Test comment with some content. Id of this comment is 99393.",
    "moderator": null,
    "moderatedDate": {
      "dayOfMonth": 9,
      "hour": 5,
      "minute": 27,
      "month": "",
      "monthValue": 2,
      "nano": 0,
      "second": 1,
      "year": 2000,
      "dayOfWeek": "",
      "dayOfYear": 212
    },
    "parentId": 0,
    "parent": null,
    "children": null,
    "user": {
      "id": 0,
      "name": "user 0",
      "emailAddress": "user0@sdl.com",
      "externalId": null
    },
    "idLong": 99393
  },
  {
    "id": 52752,
    "namespaceId": 0,
    "itemPublicationId": 1611362,
    "itemId": 368717,
    "itemType": 64,
    "score": 0,
    "status": 0,
    "creationDate": {
      "dayOfMonth": 22,
      "hour": 0,
      "minute": 24,
      "month": "",
      "monthValue": 8,
      "nano": 0,
      "second": 50,
      "year": 2008,
      "dayOfWeek": "",
      "dayOfYear": 174
    },
    "lastModifiedDate": {
      "dayOfMonth": 22,
      "hour": 0,
      "minute": 24,
      "month": "",
      "monthValue": 8,
      "nano": 0,
      "second": 50,
      "year": 2008,
      "dayOfWeek": "",
      "dayOfYear": 174
    },
    "content": "Test comment with some content. Id of this comment is 52752.",
    "moderator": null,
    "moderatedDate": {
      "dayOfMonth": 22,
      "hour": 0,
      "minute": 24,
      "month": "",
      "monthValue": 8,
      "nano": 0,
      "second": 50,
      "year": 2008,
      "dayOfWeek": "",
      "dayOfYear": 174
    },
    "parentId": 0,
    "parent": null,
    "children": null,
    "user": {
      "id": 2,
      "name": "user 2",
      "emailAddress": "user2@sdl.com",
      "externalId": null
    },
    "idLong": 52752
  },
  {
    "id": 49563,
    "namespaceId": 0,
    "itemPublicationId": 1611362,
    "itemId": 368717,
    "itemType": 64,
    "score": 0,
    "status": 0,
    "creationDate": {
      "dayOfMonth": 4,
      "hour": 15,
      "minute": 50,
      "month": "",
      "monthValue": 10,
      "nano": 0,
      "second": 23,
      "year": 2014,
      "dayOfWeek": "",
      "dayOfYear": 183
    },
    "lastModifiedDate": {
      "dayOfMonth": 4,
      "hour": 15,
      "minute": 50,
      "month": "",
      "monthValue": 10,
      "nano": 0,
      "second": 23,
      "year": 2014,
      "dayOfWeek": "",
      "dayOfYear": 183
    },
    "content": "Test comment with some content. Id of this comment is 49563.",
    "moderator": null,
    "moderatedDate": {
      "dayOfMonth": 4,
      "hour": 15,
      "minute": 50,
      "month": "",
      "monthValue": 10,
      "nano": 0,
      "second": 23,
      "year": 2014,
      "dayOfWeek": "",
      "dayOfYear": 183
    },
    "parentId": 0,
    "parent": null,
    "children": null,
    "user": {
      "id": 0,
      "name": "user 0",
      "emailAddress": "user0@sdl.com",
      "externalId": null
    },
    "idLong": 49563
  }
]