[
  {
    "id": 44758,
    "namespaceId": 0,
    "itemPublicationId": 1961681,
    "itemId": 137364,
    "itemType": 64,
    "score": 0,
    "status": 0,
    "creationDate": {
      "dayOfMonth": 8,
      "hour": 0,
      "minute": 18,
      "month": "",
      "monthValue": 7,
      "nano": 0,
      "second": 9,
      "year": 2003,
      "dayOfWeek": "",
      "dayOfYear": 90
    },
    "lastModifiedDate": {
      "dayOfMonth": 8,
      "hour": 0,
      "minute": 18,
      "month": "",
      "monthValue": 7,
      "nano": 0,
      "second": 9,
      "year": 2003,
      "dayOfWeek": "",
      "dayOfYear": 90
    },
    "content": "Test comment with some content. Id of this comment is 44758.",
    "moderator": null,
    "moderatedDate": {
      "dayOfMonth": 8,
      "hour": 0,
      "minute": 18,
      "month": "",
      "monthValue": 7,
      "nano": 0,
      "second": 9,
      "year": 2003,
      "dayOfWeek": "",
      "dayOfYear": 90
    },
    "parentId": 0,
    "parent": null,
    "children": null,
    "user": {
      "id": 0,
      "name": "user 0",
      "emailAddress": "user0@sdl.com",
      "externalId": null
    },
    "idLong": 44758
  },
  {
    "id": 93161,
    "namespaceId": 0,
    "itemPublicationId": 1961681,
    "itemId": 137364,
    "itemType": 64,
    "score": 0,
    "status": 0,
    "creationDate": {
      "dayOfMonth": 22,
      "hour": 7,
      "minute": 41,
      "month": "",
      "monthValue": 4,
      "nano": 0,
      "second": 8,
      "year": 2010,
      "dayOfWeek": "",
      "dayOfYear": 245
    },
    "lastModifiedDate": {
      "dayOfMonth": 22,
      "hour": 7,
      "minute": 41,
      "month": "",
      "monthValue": 4,
      "nano": 0,
      "second": 8,
      "year": 2010,
      "dayOfWeek": "",
      "dayOfYear": 245
    },
    "content": "Test comment with some content. Id of this comment is 93161.",
    "moderator": null,
    "moderatedDate": {
      "dayOfMonth": 22,
      "hour": 7,
      "minute": 41,
      "month": "",
      "monthValue": 4,
      "nano": 0,
      "second": 8,
      "year": 2010,
      "dayOfWeek": "",
      "dayOfYear": 245
    },
    "parentId": 0,
    "parent": null,
    "children": null,
    "user": {
      "id": 0,
      "name": "user 0",
      "emailAddress": "user0@sdl.com",
      "externalId": null
    },
    "idLong": 93161
  },
  {
    "id": 56064,
    "namespaceId": 0,
    "itemPublicationId": 1961681,
    "itemId": 137364,
    "itemType": 64,
    "score": 0,
    "status": 0,
    "creationDate": {
      "dayOfMonth": 29,
      "hour": 6,
      "minute": 16,
      "month": "",
      "monthValue": 1,
      "nano": 0,
      "second": 3,
      "year": 2013,
      "dayOfWeek": "",
      "dayOfYear": 129
    },
    "lastModifiedDate": {
      "dayOfMonth": 29,
      "hour": 6,
      "minute": 16,
      "month": "",
      "monthValue": 1,
      "nano": 0,
      "second": 3,
      "year": 2013,
      "dayOfWeek": "",
      "dayOfYear": 129
    },
    "content": "Test comment with some content. Id of this comment is 56064.",
    "moderator": null,
    "moderatedDate": {
      "dayOfMonth": 29,
      "hour": 6,
      "minute": 16,
      "month": "",
      "monthValue": 1,
      "nano": 0,
      "second": 3,
      "year": 2013,
      "dayOfWeek": "",
      "dayOfYear": 129
    },
    "parentId": 0,
    "parent": null,
    "children": null,
    "user": {
      "id": 0,
      "name": "user 0",
      "emailAddress": "user0@sdl.com",
      "externalId": null
    },
    "idLong": 56064
  },
  {
    "id": 85936,
    "namespaceId": 0,
    "itemPublicationId": 1961681,
    "itemId": 137364,
    "itemType": 64,
    "score": 0,
    "status": 0,
    "creationDate": {
      "dayOfMonth": 7,
      "hour": 1,
      "minute": 7,
      "month": "",
      "monthValue": 6,
      "nano": 0,
      "second": 0,
      "year": 2012,
      "dayOfWeek": "",
      "dayOfYear": 128
    },
    "lastModifiedDate": {
      "dayOfMonth": 7,
      "hour": 1,
      "minute": 7,
      "month": "",
      "monthValue": 6,
      "nano": 0,
      "second": 0,
      "year": 2012,
      "dayOfWeek": "",
      "dayOfYear": 128
    },
    "content": "Test comment with some content. Id of this comment is 85936.",
    "moderator": null,
    "moderatedDate": {
      "dayOfMonth": 7,
      "hour": 1,
      "minute": 7,
      "month": "",
      "monthValue": 6,
      "nano": 0,
      "second": 0,
      "year": 2012,
      "dayOfWeek": "",
      "dayOfYear": 128
    },
    "parentId": 0,
    "parent": null,
    "children": null,
    "user": {
      "id": 2,
      "name": "user 2",
      "emailAddress": "user2@sdl.com",
      "externalId": null
    },
    "idLong": 85936
  },
  {
    "id": 42909,
    "namespaceId": 0,
    "itemPublicationId": 1961681,
    "itemId": 137364,
    "itemType": 64,
    "score": 0,
    "status": 0,
    "creationDate": {
      "dayOfMonth": 14,
      "hour": 21,
      "minute": 54,
      "month": "",
      "monthValue": 3,
      "nano": 0,
      "second": 9,
      "year": 2000,
      "dayOfWeek": "",
      "dayOfYear": 278
    },
    "lastModifiedDate": {
      "dayOfMonth": 14,
      "hour": 21,
      "minute": 54,
      "month": "",
      "monthValue": 3,
      "nano": 0,
      "second": 9,
      "year": 2000,
      "dayOfWeek": "",
      "dayOfYear": 278
    },
    "content": "Test comment with some content. Id of this comment is 42909.",
    "moderator": null,
    "moderatedDate": {
      "dayOfMonth": 14,
      "hour": 21,
      "minute": 54,
      "month": "",
      "monthValue": 3,
      "nano": 0,
      "second": 9,
      "year": 2000,
      "dayOfWeek": "",
      "dayOfYear": 278
    },
    "parentId": 0,
    "parent": null,
    "children": null,
    "user": {
      "id": 0,
      "name": "user 0",
      "emailAddress": "user0@sdl.com",
      "externalId": null
    },
    "idLong": 42909
  },
  {
    "id": 30134,
    "namespaceId": 0,
    "itemPublicationId": 1961681,
    "itemId": 137364,
    "itemType": 64,
    "score": 0,
    "status": 0,
    "creationDate": {
      "dayOfMonth": 11,
      "hour": 8,
      "minute": 13,
      "month": "",
      "monthValue": 11,
      "nano": 0,
      "second": 57,
      "year": 2007,
      "dayOfWeek": "",
      "dayOfYear": 195
    },
    "lastModifiedDate": {
      "dayOfMonth": 11,
      "hour": 8,
      "minute": 13,
      "month": "",
      "monthValue": 11,
      "nano": 0,
      "second": 57,
      "year": 2007,
      "dayOfWeek": "",
      "dayOfYear": 195
    },
    "content": "Test comment with some content. Id of this comment is 30134.",
    "moderator": null,
    "moderatedDate": {
      "dayOfMonth": 11,
      "hour": 8,
      "minute": 13,
      "month": "",
      "monthValue": 11,
      "nano": 0,
      "second": 57,
      "year": 2007,
      "dayOfWeek": "",
      "dayOfYear": 195
    },
    "parentId": 0,
    "parent": null,
    "children": null,
    "user": {
      "id": 2,
      "name": "user 2",
      "emailAddress": "user2@sdl.com",
      "externalId": null
    },
    "idLong": 30134
  },
  {
    "id": 86193,
    "namespaceId": 0,
    "itemPublicationId": 1961681,
    "itemId": 137364,
    "itemType": 64,
    "score": 0,
    "status": 0,
    "creationDate": {
      "dayOfMonth": 28,
      "hour": 4,
      "minute": 57,
      "month": "",
      "monthValue": 6,
      "nano": 0,
      "second": 13,
      "year": 2005,
      "dayOfWeek": "",
      "dayOfYear": 163
    },
    "lastModifiedDate": {
      "dayOfMonth": 28,
      "hour": 4,
      "minute": 57,
      "month": "",
      "monthValue": 6,
      "nano": 0,
      "second": 13,
      "year": 2005,
      "dayOfWeek": "",
      "dayOfYear": 163
    },
    "content": "Test comment with some content. Id of this comment is 86193.",
    "moderator": null,
    "moderatedDate": {
      "dayOfMonth": 28,
      "hour": 4,
      "minute": 57,
      "month": "",
      "monthValue": 6,
      "nano": 0,
      "second": 13,
      "year": 2005,
      "dayOfWeek": "",
      "dayOfYear": 163
    },
    "parentId": 0,
    "parent": null,
    "children": null,
    "user": {
      "id": 0,
      "name": "user 0",
      "emailAddress": "user0@sdl.com",
      "externalId": null
    },
    "idLong": 86193
  },
  {
    "id": 2972,
    "namespaceId": 0,
    "itemPublicationId": 1961681,
    "itemId": 137364,
    "itemType": 64,
    "score": 0,
    "status": 0,
    "creationDate": {
      "dayOfMonth": 27,
      "hour": 4,
      "minute": 19,
      "month": "",
      "monthValue": 11,
      "nano": 0,
      "second": 59,
      "year": 2012,
      "dayOfWeek": "",
      "dayOfYear": 180
    },
    "lastModifiedDate": {
      "dayOfMonth": 27,
      "hour": 4,
      "minute": 19,
      "month": "",
      "monthValue": 11,
      "nano": 0,
      "second": 59,
      "year": 2012,
      "dayOfWeek": "",
      "dayOfYear": 180
    },
    "content": "Test comment with some content. Id of this comment is 2972.",
    "moderator": null,
    "moderatedDate": {
      "dayOfMonth": 27,
      "hour": 4,
      "minute": 19,
      "month": "",
      "monthValue": 11,
      "nano": 0,
      "second": 59,
      "year": 2012,
      "dayOfWeek": "",
      "dayOfYear": 180
    },
    "parentId": 0,
    "parent": null,
    "children": null,
    "user": {
      "id": 2,
      "name": "user 2",
      "emailAddress": "user2@sdl.com",
      "externalId": null
    },
    "idLong": 2972
  }
]