[
  {
    "id": 1898087500,
    "namespaceId": 0,
    "itemPublicationId": 1881665,
    "itemId": 164225,
    "itemType": 64,
    "score": 0,
    "status": 0,
    "creationDate": {
      "dayOfMonth": 10,
      "hour": 11,
      "minute": 40,
      "month": "",
      "monthValue": 5,
      "nano": 0,
      "second": 40,
      "year": 2015,
      "dayOfWeek": "",
      "dayOfYear": 266
    },
    "lastModifiedDate": {
      "dayOfMonth": 10,
      "hour": 11,
      "minute": 40,
      "month": "",
      "monthValue": 5,
      "nano": 0,
      "second": 40,
      "year": 2015,
      "dayOfWeek": "",
      "dayOfYear": 266
    },
    "content": "Test comment with some content. Id of this comment is 1898087500.",
    "moderator": null,
    "moderatedDate": {
      "dayOfMonth": 10,
      "hour": 11,
      "minute": 40,
      "month": "",
      "monthValue": 5,
      "nano": 0,
      "second": 40,
      "year": 2015,
      "dayOfWeek": "",
      "dayOfYear": 266
    },
    "parentId": 0,
    "parent": null,
    "children": null,
    "user": {
      "id": 2,
      "name": "user 2",
      "emailAddress": "user2@sdl.com",
      "externalId": null
    },
    "idLong": 1898087500
  },
  {
    "id": 1898087501,
    "namespaceId": 0,
    "itemPublicationId": 1881665,
    "itemId": 164225,
    "itemType": 64,
    "score": 0,
    "status": 0,
    "creationDate": {
      "dayOfMonth": 11,
      "hour": 12,
      "minute": 41,
      "month": "",
      "monthValue": 6,
      "nano": 0,
      "second": 41,
      "year": 2016,
      "dayOfWeek": "",
      "dayOfYear": 267
    },
    "lastModifiedDate": {
      "dayOfMonth": 11,
      "hour": 12,
      "minute": 41,
      "month": "",
      "monthValue": 6,
      "nano": 0,
      "second": 41,
      "year": 2016,
      "dayOfWeek": "",
      "dayOfYear": 267
    },
    "content": "Test comment with some content. Id of this comment is 1898087501.",
    "moderator": null,
    "moderatedDate": {
      "dayOfMonth": 11,
      "hour": 12,
      "minute": 41,
      "month": "",
      "monthValue": 6,
      "nano": 0,
      "second": 41,
      "year": 2016,
      "dayOfWeek": "",
      "dayOfYear": 267
    },
    "parentId": 0,
    "parent": null,
    "children": null,
    "user": {
      "id": 3,
      "name": "user 3",
      "emailAddress": "user3@sdl.com",
      "externalId": null
    },
    "idLong": 1898087501
  },
  {
    "id": 1898087502,
    "namespaceId": 0,
    "itemPublicationId": 1881665,
    "itemId": 164225,
    "itemType": 64,
    "score": 0,
    "status": 0,
    "creationDate": {
      "dayOfMonth": 12,
      "hour": 13,
      "minute": 42,
      "month": "",
      "monthValue": 7,
      "nano": 0,
      "second": 42,
      "year": 2000,
      "dayOfWeek": "",
      "dayOfYear": 268
    },
    "lastModifiedDate": {
      "dayOfMonth": 12,
      "hour": 13,
      "minute": 42,
      "month": "",
      "monthValue": 7,
      "nano": 0,
      "second": 42,
      "year": 2000,
      "dayOfWeek": "",
      "dayOfYear": 268
    },
    "content": "Test comment with some content. Id of this comment is 1898087502.",
    "moderator": null,
    "moderatedDate": {
      "dayOfMonth": 12,
      "hour": 13,
      "minute": 42,
      "month": "",
      "monthValue": 7,
      "nano": 0,
      "second": 42,
      "year": 2000,
      "dayOfWeek": "",
      "dayOfYear": 268
    },
    "parentId": 0,
    "parent": null,
    "children": [
      {
        "id": 1898087500,
        "namespaceId": 0,
        "itemPublicationId": 1881665,
        "itemId": 164225,
        "itemType": 64,
        "score": 0,
        "status": 0,
        "creationDate": {
          "dayOfMonth": 10,
          "hour": 11,
          "minute": 40,
          "month": "",
          "monthValue": 5,
          "nano": 0,
          "second": 40,
          "year": 2015,
          "dayOfWeek": "",
          "dayOfYear": 266
        },
        "lastModifiedDate": {
          "dayOfMonth": 10,
          "hour": 11,
          "minute": 40,
          "month": "",
          "monthValue": 5,
          "nano": 0,
          "second": 40,
          "year": 2015,
          "dayOfWeek": "",
          "dayOfYear": 266
        },
        "content": "Test comment with some content. Id of this comment is 1898087500.",
        "moderator": null,
        "moderatedDate": {
          "dayOfMonth": 10,
          "hour": 11,
          "minute": 40,
          "month": "",
          "monthValue": 5,
          "nano": 0,
          "second": 40,
          "year": 2015,
          "dayOfWeek": "",
          "dayOfYear": 266
        },
        "parentId": 0,
        "parent": null,
        "children": null,
        "user": {
          "id": 2,
          "name": "user 2",
          "emailAddress": "user2@sdl.com",
          "externalId": null
        },
        "idLong": 1898087500
      },
      {
        "id": 1898087501,
        "namespaceId": 0,
        "itemPublicationId": 1881665,
        "itemId": 164225,
        "itemType": 64,
        "score": 0,
        "status": 0,
        "creationDate": {
          "dayOfMonth": 11,
          "hour": 12,
          "minute": 41,
          "month": "",
          "monthValue": 6,
          "nano": 0,
          "second": 41,
          "year": 2016,
          "dayOfWeek": "",
          "dayOfYear": 267
        },
        "lastModifiedDate": {
          "dayOfMonth": 11,
          "hour": 12,
          "minute": 41,
          "month": "",
          "monthValue": 6,
          "nano": 0,
          "second": 41,
          "year": 2016,
          "dayOfWeek": "",
          "dayOfYear": 267
        },
        "content": "Test comment with some content. Id of this comment is 1898087501.",
        "moderator": null,
        "moderatedDate": {
          "dayOfMonth": 11,
          "hour": 12,
          "minute": 41,
          "month": "",
          "monthValue": 6,
          "nano": 0,
          "second": 41,
          "year": 2016,
          "dayOfWeek": "",
          "dayOfYear": 267
        },
        "parentId": 0,
        "parent": null,
        "children": null,
        "user": {
          "id": 3,
          "name": "user 3",
          "emailAddress": "user3@sdl.com",
          "externalId": null
        },
        "idLong": 1898087501
      }
    ],
    "user": {
      "id": 1,
      "name": "user 1",
      "emailAddress": "user1@sdl.com",
      "externalId": null
    },
    "idLong": 1898087502
  },
  {
    "id": 1898087503,
    "namespaceId": 0,
    "itemPublicationId": 1881665,
    "itemId": 164225,
    "itemType": 64,
    "score": 0,
    "status": 0,
    "creationDate": {
      "dayOfMonth": 13,
      "hour": 14,
      "minute": 43,
      "month": "",
      "monthValue": 8,
      "nano": 0,
      "second": 43,
      "year": 2001,
      "dayOfWeek": "",
      "dayOfYear": 269
    },
    "lastModifiedDate": {
      "dayOfMonth": 13,
      "hour": 14,
      "minute": 43,
      "month": "",
      "monthValue": 8,
      "nano": 0,
      "second": 43,
      "year": 2001,
      "dayOfWeek": "",
      "dayOfYear": 269
    },
    "content": "Test comment with some content. Id of this comment is 1898087503.",
    "moderator": null,
    "moderatedDate": {
      "dayOfMonth": 13,
      "hour": 14,
      "minute": 43,
      "month": "",
      "monthValue": 8,
      "nano": 0,
      "second": 43,
      "year": 2001,
      "dayOfWeek": "",
      "dayOfYear": 269
    },
    "parentId": 0,
    "parent": null,
    "children": null,
    "user": {
      "id": 2,
      "name": "user 2",
      "emailAddress": "user2@sdl.com",
      "externalId": null
    },
    "idLong": 1898087503
  },
  {
    "id": 1898087504,
    "namespaceId": 0,
    "itemPublicationId": 1881665,
    "itemId": 164225,
    "itemType": 64,
    "score": 0,
    "status": 0,
    "creationDate": {
      "dayOfMonth": 14,
      "hour": 15,
      "minute": 44,
      "month": "",
      "monthValue": 9,
      "nano": 0,
      "second": 44,
      "year": 2002,
      "dayOfWeek": "",
      "dayOfYear": 270
    },
    "lastModifiedDate": {
      "dayOfMonth": 14,
      "hour": 15,
      "minute": 44,
      "month": "",
      "monthValue": 9,
      "nano": 0,
      "second": 44,
      "year": 2002,
      "dayOfWeek": "",
      "dayOfYear": 270
    },
    "content": "Test comment with some content. Id of this comment is 1898087504.",
    "moderator": null,
    "moderatedDate": {
      "dayOfMonth": 14,
      "hour": 15,
      "minute": 44,
      "month": "",
      "monthValue": 9,
      "nano": 0,
      "second": 44,
      "year": 2002,
      "dayOfWeek": "",
      "dayOfYear": 270
    },
    "parentId": 0,
    "parent": null,
    "children": null,
    "user": {
      "id": 3,
      "name": "user 3",
      "emailAddress": "user3@sdl.com",
      "externalId": null
    },
    "idLong": 1898087504
  }
]