{
  "Id": "ish:39137-6229-16",
  "Title": "saving names and numbers",
  "Meta": {
    "ishlngref.object.id": 6229,
    "ishversionref.object.id": 6227,
    "ishlogicalref.object.id": 6226,
    "ishref.object.value": "GUID-67F1627E-FFBA-4E03-A62D-F70030C52596",
    "ishtype.object.value": "ISHModule",
    "FTITLE.logical.value": "saving names and numbers",
    "FDESCRIPTION.logical.value": null,
    "FCHANGES.version.value": "Imported OASIS DITA 1.1",
    "FISHRELEASELABEL.version.value": null,
    "CREATED-ON.lng.value": "2008-10-29T16:09:58Z",
    "FAUTHOR.lng.value": "Author",
    "FSTATUS.lng.value": "Released",
    "MODIFIED-ON.lng.value": "2010-04-09T08:26:09Z",
    "VERSION.version.value": "1",
    "FRESOLUTION.lng.value": null,
    "DOC-LANGUAGE.lng.value": [
      "en"
    ],
    "FISHREVCOUNTER.lng.value": 1,
    "ED.lng.value": [
      "GUID-E17EDE47-A8D5-4072-9FB2-C79607D6C243"
    ],
    "FUSERGROUP.logical.value": null,
    "READ-ACCESS.logical.value": null
  },
  "Html": "\n\t\t<h1 class=\"title topictitle1\" id=\"GUID-67F1627E-FFBA-4E03-A62D-F70030C52596__GUID-91208EF2-9DF8-4968-95C3-7B281273B8A0\" xmlns=\"http://www.w3.org/1999/xhtml\">Saving names and numbers</h1>\n\t\t<div class=\"body taskbody\" xmlns=\"http://www.w3.org/1999/xhtml\">\n\t\t\t<p class=\"shortdesc\">\n\t\t\t</p>\n\t\t\t<ol class=\"ol steps\" id=\"GUID-67F1627E-FFBA-4E03-A62D-F70030C52596__GUID-39CCD92E-A42F-4E2C-AE5D-9BAA72560320\">\n\t\t\t\t<li class=\"li step stepexpand\">\n\t\t\t\t\t<span class=\"ph cmd\">Press <samp class=\"ph msgph\">Contacts</samp> (or press Go to and select <samp class=\"ph msgph\">Contacts</samp>) and select <samp class=\"ph msgph\">Add contact</samp>.</span>\n\t\t\t\t</li>\n\t\t\t\t<li class=\"li step stepexpand\">\n\t\t\t\t\t<span class=\"ph cmd\">Key in the name and press <samp class=\"ph msgph\">OK</samp>.</span>\n\t\t\t\t</li>\n\t\t\t\t<li class=\"li step stepexpand\">\n\t\t\t\t\t<span class=\"ph cmd\">Key in the phone number, and press <samp class=\"ph msgph\">OK</samp>.</span>\n\t\t\t\t</li>\n\t\t\t\t<li class=\"li step stepexpand\">\n\t\t\t\t\t<span class=\"ph cmd\">When the name and number are saved, press <samp class=\"ph msgph\">Done</samp>.</span>\n\t\t\t\t\t<div class=\"itemgroup info\"> Quick save In standby mode, key in the phone number. Press <samp class=\"ph msgph\">Options</samp>, and select <samp class=\"ph msgph\">Save</samp>. Key in the name, press <samp class=\"ph msgph\">OK</samp> and <samp class=\"ph msgph\">Done</samp>.\n               </div>\n\t\t\t\t</li>\n\t\t\t</ol>\n\t\t</div>\n\t\t<div class=\"related-links\" xmlns=\"http://www.w3.org/1999/xhtml\">\n\t\t\t<div class=\"familylinks\">\n\t\t\t\t<div class=\"parentlink\">\n\t\t\t\t\t<strong>Parent topic:</strong>\n\t\t\t\t\t<a title=\"Phone book\" href=\"ish:39137-6274-16\">Phone book</a>\n\t\t\t\t</div>\n\t\t\t</div>\n\t\t</div>\n\t"
}