{
  "Id": "164415",
  "Meta": {
    "conditionsused.generated.value": null,
    "tocnaventries.generated.value": "ish:1961700-29-1024"
  },
  "Regions": [
    {
      "Entities": [
        {
          "Id": "164415",
          "topicTitle": "Snake 2",
          "topicBody": {
            "Fragments": [
              {
                "Html": "\n      \n      \n      <h1 class=\"title topictitle1\" id=\"GUID-E97722D1-514C-4FAE-A9BA-DB55C6CA04E0__GUID-D84C5D02-4DE3-4049-956D-7564DBDE9FAC\" xmlns=\"http://www.w3.org/1999/xhtml\">Snake 2</h1>\n      \n      \n      \n      <div class=\"body\" xmlns=\"http://www.w3.org/1999/xhtml\">\n         <p class=\"shortdesc\">Führe die Slange zu ihrem Futter, damit sie wächst.</p>\n         \n         <br /><img class=\"image\" src=\"/app/gui/mocks/bin/1961700-345743-16.gif\" /><br />\n         \n         <p class=\"p\">Führe die Slange zu ihrem Futter, damit sie wächst.</p>\n         \n         \n         <p class=\"p\">Mit den Tasten <img class=\"image\" src=\"/app/gui/mocks/bin/1961700-345767-16.gif\" />,<img class=\"image\" src=\"/app/gui/mocks/bin/1961700-345787-16.gif\" />,<img class=\"image\" src=\"/app/gui/mocks/bin/1961700-345939-16.gif\" /> oder <img class=\"image\" src=\"/app/gui/mocks/bin/1961700-345955-16.gif\" /> wird die Richtung geändert.\n         </p>\n         \n         \n         <p class=\"p\">Die Slange darf nicht mit der Wand oder mit sich selbst kollidieren.</p>\n         \n         \n         <p class=\"p\">Schnappe die Bonus Leckerbissen, bevor die Zeit abgelaufen ist. Unterwegs stösst die Slange auf einige Spezialobjekte. Diese\n            Objekte können das Spiel zwischenzeitlich erleichtern oder erschweren.\n         </p>\n         \n         \n      </div>\n      \n      \n      <div class=\"related-links\" xmlns=\"http://www.w3.org/1999/xhtml\">\n         \n         <div class=\"familylinks\">\n            \n            <div class=\"parentlink\"><strong>Übergeordnetes Thema:</strong> <a class=\"link\" title=\"Ihr Telefon unterstützt die Java 2 Micro Edition (J2METM), eine Version der Java-Technik, die speziell für kleine Elektronikgeräte für Endanwender entwickelt wurde. Das Telefon enthält einige Java-Programme und -Spiele und unterstützt das Herunterladen von neuen Programmen und Spielen über verschiedene WAPDienste.\" href=\"/app/1961700/164237/user-guide/spiele\">Spiele</a></div>\n            \n         </div>\n         \n      </div>\n   "
              }
            ]
          }
        }
      ]
    }
  ]
}