{
  "Id": "164157",
  "Meta": {
    "tocnaventries.generated.value": "ish:1881665-6-1024"
  },
  "Regions": [
    {
      "Entities": [
        {
          "Id": "164157",
          "topicTitle": "Aansluitingen",
          "topicBody": {
            "Fragments": [
              {
                "Html": "\n      \n      \n      <h1 class=\"title topictitle1\" id=\"GUID-03AB2EA1-F81B-4A22-8149-710094BE1081__GUID-4E0EC990-B468-401D-9D7B-9B5BEE368FED\" xmlns=\"http://www.w3.org/1999/xhtml\">Aansluitingen</h1>\n      \n      \n      \n      <div class=\"body\" xmlns=\"http://www.w3.org/1999/xhtml\">\n         <p class=\"shortdesc\" />\n         \n         \n         <tcdl:If type=\"ish:Condition\" condition=\"(MODEL=330)\" xmlns:tcdl=\"http://www.sdl.com/web/DXA/Format\"><div class=\"section\" id=\"GUID-03AB2EA1-F81B-4A22-8149-710094BE1081__GUID-150A560B-A3B1-43A7-BE5C-F2251CC62CA1\">\n            <br /><img class=\"image\" src=\"/app/gui/mocks/bin/1881665-345907-16.jpg\" /><br />\n            \n            <ol class=\"ol\" id=\"GUID-03AB2EA1-F81B-4A22-8149-710094BE1081__GUID-AF0060CD-91E5-40D6-A175-E8ABEBBCBAE2\">\n               \n               <li class=\"li\">Aansluiting voor de lader</li>\n               \n               \n               <li class=\"li\">Aansluiting voor hoofdtelefoon, verbindingskabel en hoorapparaat.</li>\n               \n               \n               <li class=\"li\">Audio lijn-in-aansluiting voor de audiokabel om de telefoon aan te sluiten op externe audioapparatuur.</li>\n               \n               \n            </ol>\n            \n            \n         </div></tcdl:If>\n         \n         \n         \n      </div>\n      \n      \n      <div class=\"related-links\" xmlns=\"http://www.w3.org/1999/xhtml\">\n         \n         <div class=\"familylinks\">\n            \n            <div class=\"parentlink\"><strong>Hoofdonderwerp:</strong> <a class=\"link\" href=\"/app/1881665/164233/user-guide/de-telefoon\">De telefoon</a></div>\n            \n         </div>\n         \n         \n         <div class=\"linklist linklist relinfo relconcepts\"><strong>Verwante onderwerpen</strong><br />\n            \n            \n            <div><a class=\"link\" title=\"Wanneer de telefoon gereed is voor gebruik en geen tekens zijn ingevoerd, bevindt de telefoon zich in de standby-modus. De naam/logo van de exploitant van uw telefoonnetwerk verschijnt in het display.\" href=\"/app/1881665/164189/user-guide/standby-modus\">Standby-modus</a></div>\n         </div>\n         \n         \n         <div class=\"linklist linklist relinfo reltasks\"><strong>Verwante taken</strong><br />\n            \n            \n            <div><a class=\"link\" href=\"/app/1881665/164273/user-guide/de-sim-kaart-en-de-batterij-installeren\">De SIM-kaart en de batterij installeren</a></div>\n            \n            <div><a class=\"link\" href=\"/app/1881665/164292/user-guide/de-batterij-opladen-\">De batterij opladen.</a></div>\n            \n            <div><a class=\"link\" href=\"/app/1881665/164257/user-guide/belangrijke-indicatoren-in-de-standby-modus\">Belangrijke indicatoren in de standby-modus</a></div>\n         </div>\n         \n      </div>\n   "
              }
            ]
          }
        }
      ]
    }
  ]
}