{
  "Id": "368525",
  "Meta": {
    "conditionsused.generated.value": null,
    "tocnaventries.generated.value": "ish:1611362-36-1024"
  },
  "Regions": [
    {
      "Entities": [
        {
          "Id": "368525",
          "topicTitle": "リファレンス・タイトルを入力してください",
          "topicBody": {
            "Fragments": [
              {
                "Html": "\n      \n      \n      <h1 class=\"title topictitle1\" id=\"GUID-01168ECC-3BF4-4764-9EEC-0808B2625F53__GUID-65C39F01-CE7D-415D-8CAF-F7D0A3FCA821\" xmlns=\"http://www.w3.org/1999/xhtml\">リファレンス・タイトルを入力してください</h1>\n      \n      \n      \n      <div class=\"body refbody\" xmlns=\"http://www.w3.org/1999/xhtml\">\n         <p class=\"shortdesc\">簡単な説明を入力してください (任意)</p>\n         \n         \n         <div class=\"section\" id=\"GUID-01168ECC-3BF4-4764-9EEC-0808B2625F53__GUID-B2E47C5F-95E8-40EB-A35D-6BA0611D66AA\">実際の情報をこのセクションに入力してください (任意)</div>\n         \n         \n         <div class=\"example\" id=\"GUID-01168ECC-3BF4-4764-9EEC-0808B2625F53__GUID-A912E43F-A7C8-46AC-A71A-71A2B69E78CF\">実例を入力してください (任意)</div>\n         \n         \n      </div>\n      \n      \n      <div class=\"related-links\" xmlns=\"http://www.w3.org/1999/xhtml\">\n         \n         <div class=\"familylinks\">\n            \n            <div class=\"parentlink\"><strong>親トピック:</strong> <a class=\"link\" title=\"簡単な説明を入力して下さい(任意)\" href=\"/app/1611362/368625/ls40-el/%e3%83%88%e3%83%92%e3%83%83%e3%82%af%e3%83%bb%e3%82%bf%e3%82%a4%e3%83%88%e3%83%ab%e3%82%92%e5%85%a5%e5%8a%9b%e3%81%97%e3%81%a6%e4%b8%8b%e3%81%95%e3%81%84\">トピック・タイトルを入力して下さい</a></div>\n            \n         </div>\n         \n      </div>\n   "
              }
            ]
          }
        }
      ]
    }
  ]
}