[
  {
    "Id": "ish:1656868-4-1024",
    "Title": "Toetsen",
    "Url": "ish:1656868-164284-16",
    "IsAbstract": false,
    "HasChildNodes": false,
    "Items": []
  },
  {
    "Id": "ish:1656868-5-1024",
    "Title": "Aansluitingen",
    "Url": "ish:1656868-164157-16",
    "IsAbstract": false,
    "HasChildNodes": false,
    "Items": []
  },
  {
    "Id": "ish:1656868-6-1024",
    "Title": "Standby-modus",
    "Url": "ish:1656868-164189-16",
    "IsAbstract": false,
    "HasChildNodes": false,
    "Items": []
  },
  {
    "Id": "ish:1656868-7-1024",
    "Title": "Belangrijke indicatoren in de standby-modus",
    "Url": "ish:1656868-164257-16",
    "IsAbstract": false,
    "HasChildNodes": false,
    "Items": []
  },
  {
    "Id": "ish:1656868-8-1024",
    "Title": "Screensaver",
    "Url": "ish:1656868-164438-16",
    "IsAbstract": false,
    "HasChildNodes": false,
    "Items": []
  },
  {
    "Id": "ish:1656868-9-1024",
    "Title": "General Packet Radio Service (GPRS)",
    "Url": "ish:1656868-164173-16",
    "IsAbstract": false,
    "HasChildNodes": false,
    "Items": []
  },
  {
    "Id": "ish:1656868-10-1024",
    "Title": "Bluetooth-verbinding",
    "Url": "ish:1656868-164311-16",
    "IsAbstract": false,
    "HasChildNodes": false,
    "Items": []
  }
]